MahjongGB.cp37-win_amd64.pyd
PyMahjongGB-1.1.0.dist-info/LICENSE
PyMahjongGB-1.1.0.dist-info/METADATA
PyMahjongGB-1.1.0.dist-info/WHEEL
PyMahjongGB-1.1.0.dist-info/top_level.txt
PyMahjongGB-1.1.0.dist-info/RECORD
