Metadata-Version: 2.1
Name: PyMahjongGB
Version: 1.1.0
Summary: A library for Fan Calculation of Mahjong in Chinese Standard Rule.
Home-page: https://github.com/ailab-pku/MahjongGB
Author: Yunlong Lu
Author-email: luyunlong@pku.edu.cn
License: UNKNOWN
Platform: UNKNOWN
Requires-Python: >=3.5
